src/AI.py
src/__init__.py
src/auth.py
src/controls.py
src/driver_setup.py
src/google_meet_bot.py
src/main.py
src/question_checker.py
src/subtitle_saver.py
src/subtitle_saver_ch.py
src/subtitle_saver_fa.py
src/subtitle_saver_fr.py
src/test.py
src/translator.py
meetma-0.0.2.dist-info/LICENSE
meetma-0.0.2.dist-info/METADATA
meetma-0.0.2.dist-info/WHEEL
meetma-0.0.2.dist-info/entry_points.txt
meetma-0.0.2.dist-info/top_level.txt
meetma-0.0.2.dist-info/RECORD
